system_pyside6.pth
system_pyside6.py
system_pyside6-0.1.1.dist-info/licenses/LICENSE
system_pyside6-0.1.1.dist-info/METADATA
system_pyside6-0.1.1.dist-info/WHEEL
system_pyside6-0.1.1.dist-info/top_level.txt
system_pyside6-0.1.1.dist-info/RECORD
