Metadata-Version: 2.4
Name: system-pyside6
Version: 0.1.1
Summary: A Python package that exposes system-installed PySide6 packages into a virtual environment.
Author-email: Russell Keith-Magee <russell@keith-magee.com>
Maintainer-email: BeeWare Team <team@beeware.org>
License-Expression: BSD-3-Clause
Project-URL: Homepage, https://beeware.org/system-pyside6
Project-URL: Funding, https://beeware.org/contributing/membership/
Project-URL: Documentation, https://system-pyside6.readthedocs.io/en/latest/
Project-URL: Tracker, https://github.com/beeware/system-pyside6/issues
Project-URL: Source, https://github.com/beeware/system-pyside6
Keywords: PySide6,Qt,venv
Classifier: Development Status :: 3 - Alpha
Classifier: Environment :: X11 Applications :: KDE
Classifier: Environment :: X11 Applications :: Qt
Classifier: Intended Audience :: Developers
Classifier: Operating System :: OS Independent
Classifier: Programming Language :: Python :: 3
Classifier: Programming Language :: Python :: 3.10
Classifier: Programming Language :: Python :: 3.11
Classifier: Programming Language :: Python :: 3.12
Classifier: Programming Language :: Python :: 3.13
Classifier: Programming Language :: Python :: 3.14
Classifier: Programming Language :: Python :: 3 :: Only
Classifier: Topic :: Software Development
Classifier: Topic :: Utilities
Requires-Python: >=3.10
License-File: LICENSE
Dynamic: license-file
